collective.googlenews-2.0b3-py2.7-nspkg.pth
collective/googlenews/__init__.py
collective/googlenews/config.py
collective/googlenews/configure.zcml
collective/googlenews/controlpanel.png
collective/googlenews/controlpanel.py
collective/googlenews/interfaces.py
collective/googlenews/logger.py
collective/googlenews/patches.py
collective/googlenews/profiles.zcml
collective/googlenews/setuphandlers.py
collective/googlenews/testing.py
collective/googlenews/testing.zcml
collective/googlenews/utils.py
collective/googlenews/Extensions/Install.py
collective/googlenews/Extensions/__init__.py
collective/googlenews/behaviors/__init__.py
collective/googlenews/behaviors/configure.zcml
collective/googlenews/behaviors/interfaces.py
collective/googlenews/browser/__init__.py
collective/googlenews/browser/configure.zcml
collective/googlenews/browser/meta.pt
collective/googlenews/browser/sitemap.pt
collective/googlenews/browser/sitemap.py
collective/googlenews/browser/viewlets.py
collective/googlenews/browser/views.py
collective/googlenews/browser/warning.pt
collective/googlenews/locales/collective.googlenews.pot
collective/googlenews/locales/manual.pot
collective/googlenews/locales/plone.pot
collective/googlenews/locales/es/LC_MESSAGES/collective.googlenews.po
collective/googlenews/locales/es/LC_MESSAGES/plone.po
collective/googlenews/locales/fr/LC_MESSAGES/collective.googlenews.po
collective/googlenews/locales/fr/LC_MESSAGES/plone.po
collective/googlenews/locales/pt_BR/LC_MESSAGES/collective.googlenews.po
collective/googlenews/locales/pt_BR/LC_MESSAGES/plone.po
collective/googlenews/profiles/default/browserlayer.xml
collective/googlenews/profiles/default/catalog.xml
collective/googlenews/profiles/default/collective.googlenews.marker.txt
collective/googlenews/profiles/default/controlpanel.xml
collective/googlenews/profiles/default/metadata.xml
collective/googlenews/profiles/default/registry.xml
collective.googlenews-2.0b3.dist-info/DESCRIPTION.rst
collective.googlenews-2.0b3.dist-info/METADATA
collective.googlenews-2.0b3.dist-info/RECORD
collective.googlenews-2.0b3.dist-info/WHEEL
collective.googlenews-2.0b3.dist-info/entry_points.txt
collective.googlenews-2.0b3.dist-info/metadata.json
collective.googlenews-2.0b3.dist-info/namespace_packages.txt
collective.googlenews-2.0b3.dist-info/top_level.txt
