Metadata-Version: 2.0
Name: collective.googlenews
Version: 2.0b3
Summary: Make easy to add your Plone site to Google News.
Home-page: https://github.com/collective/collective.googlenews
Author: JeanMichel FRANCOIS aka toutpt
Author-email: toutpt@gmail.com
License: GPLv2
Keywords: plone google
Platform: UNKNOWN
Classifier: Development Status :: 4 - Beta
Classifier: Environment :: Web Environment
Classifier: Framework :: Plone
Classifier: Framework :: Plone :: 4.3
Classifier: Framework :: Plone :: 5.0
Classifier: Intended Audience :: System Administrators
Classifier: License :: OSI Approved :: GNU General Public License v2 (GPLv2)
Classifier: Operating System :: OS Independent
Classifier: Programming Language :: Python
Classifier: Programming Language :: Python :: 2.7
Classifier: Topic :: Office/Business :: News/Diary
Classifier: Topic :: Software Development :: Libraries :: Python Modules
Requires-Dist: Products.CMFCore
Requires-Dist: Products.CMFPlone (>=4.3)
Requires-Dist: Products.GenericSetup
Requires-Dist: collective.monkeypatcher
Requires-Dist: plone.api (>=1.5)
Requires-Dist: plone.app.dexterity
Requires-Dist: plone.app.layout
Requires-Dist: plone.app.registry
Requires-Dist: plone.behavior
Requires-Dist: plone.dexterity
Requires-Dist: plone.formwidget.namedfile (>=1.0.12)
Requires-Dist: plone.namedfile
Requires-Dist: plone.supermodel
Requires-Dist: setuptools
Requires-Dist: zope.i18nmessageid
Requires-Dist: zope.interface
Requires-Dist: zope.schema
Provides-Extra: test
Requires-Dist: AccessControl; extra == 'test'
Requires-Dist: plone.app.robotframework; extra == 'test'
Requires-Dist: plone.app.testing[robot]; extra == 'test'
Requires-Dist: plone.browserlayer; extra == 'test'
Requires-Dist: plone.registry; extra == 'test'
Requires-Dist: zope.component; extra == 'test'
